pmoschos_art_gen/__init__.py
pmoschos_art_gen/ascii_generator.py
pmoschos_art_gen/cli.py
pmoschos_art_gen-0.1.1.dist-info/licenses/LICENSE
pmoschos_art_gen-0.1.1.dist-info/METADATA
pmoschos_art_gen-0.1.1.dist-info/WHEEL
pmoschos_art_gen-0.1.1.dist-info/entry_points.txt
pmoschos_art_gen-0.1.1.dist-info/top_level.txt
pmoschos_art_gen-0.1.1.dist-info/RECORD
