Metadata-Version: 2.4
Name: pmoschos_art_gen
Version: 0.1.1
Summary: Rainbow ASCII Art Generator
Author-email: Panagiotis Moschos <pan.moschos86@gmail.com>
License: MIT
Project-URL: Homepage, https://github.com/pmoschos/pmoschos_art_gen
Project-URL: Bug Tracker, https://github.com/pmoschos/pmoschos_art_gen/issues
Classifier: Programming Language :: Python :: 3
Classifier: License :: OSI Approved :: MIT License
Classifier: Operating System :: OS Independent
Requires-Python: >=3.7
License-File: LICENSE
Requires-Dist: art>=5.6
Requires-Dist: colorama>=0.4.4
Dynamic: license-file
